kompatible/__init__.py
kompatible/api.py
kompatible/client.py
kompatible/containers.py
kompatible/images.py
kompatible/volumes.py
kompatible-0.0.2.dist-info/LICENSE
kompatible-0.0.2.dist-info/METADATA
kompatible-0.0.2.dist-info/WHEEL
kompatible-0.0.2.dist-info/top_level.txt
kompatible-0.0.2.dist-info/RECORD
