Metadata-Version: 2.1
Name: kompatible
Version: 0.0.2
Summary: Python wrapper for Kubernetes which matches the interface of Docker
Home-page: https://github.com/refinery-platform/kompatible/
Author: Chuck McCallum
License: MIT License
Platform: UNKNOWN
Classifier: Intended Audience :: Developers
Classifier: License :: OSI Approved :: MIT License
Classifier: Operating System :: OS Independent
Classifier: Programming Language :: Python
Requires-Dist: kubernetes (>=4.0.0)
